FPGA/IP_repo/timestamping_unit/src/timestamping_unit.vhd
-- //////////////////////////////////////////////////////////////////////////////////
-- // Engineer: Abdelrahman Hewala (Shiro)
-- //
-- // Design Name: spi_master_adcs7476
-- // Project Name: EKF by HLS
-- // Target Devices: Xilinx Basys 3
-- // Tool Versions: Vivado 2026.1
-- //
-- // Description:
-- //   This ip is jsut a simple counter that increase by 1 with every
-- //   Tick of the input clk. its output is the counter current value.
-- //   This value is being used as a global time stamp for the whole design
-- //   and get latched for each new IMU reading. it is design to run on 100 MHz clk
-- //
-- // Revision 0.01 - File Created
-- // VHDL Version: VHDL-2008
-- //////////////////////////////////////////////////////////////////////////////////
library ieee;
use ieee.std_logic_1164.all;
use ieee.numeric_std.all;

entity timestamping_unit is
    generic(
        TIMESTAMP_WIDTH : natural := 64
    );

    port(
        clk    : in  std_logic;
        rst_n  : in  std_logic;    -- active-low synchronous reset

        time_stamp : out std_logic_vector(TIMESTAMP_WIDTH - 1 downto 0)
    );
end entity timestamping_unit;

architecture rtl of timestamping_unit is

    signal counter : unsigned(TIMESTAMP_WIDTH - 1 downto 0) := (others => '0');

begin
    time_stamp <= std_logic_vector(counter);

    counter_p : process(clk) is 
    begin 
        if rising_edge(clk) then 
            if rst_n = '0' then
                counter <= (others => '0');
            else
                counter <= counter + 1;
            end if;
        end if;  
    end process counter_p;
    
end architecture rtl;

FPGA/IP_repo/timestamping_unit/tb/tb_timestamping_unit.vhd
-- //////////////////////////////////////////////////////////////////////////////////
-- // Engineer: Abdelrahman Hewala (Shiro)
-- // Testbench for: timestamping_unit
-- // Project Name: EKF by HLS
-- // Tool: GHDL --std=08
-- //
-- // Description:
-- //   Self-checking testbench for the free-running timestamp counter.
-- //   Uses an 8-bit instance of the DUT (TIMESTAMP_WIDTH is just the width of a plain
-- //   unsigned counter, so behaviour is generic-independent -- an 8-bit instance lets
-- //   us actually exercise the wrap-around path in a sane number of clock cycles,
-- //   something that's impossible to do directly on the real 64-bit instance).
-- //   A second, separate instance at the real design's default width (64) free-runs
-- //   alongside the 8-bit one the whole test, to confirm the default-generic
-- //   configuration used in the real design compiles and counts correctly too.
-- //
-- //   Both DUTs are advanced through one shared "tick" procedure that mirrors the
-- //   DUT's own reset/increment behaviour as a golden reference model -- this avoids
-- //   the classic VHDL gotcha of reading a signal in the same delta cycle as its own
-- //   scheduled assignment (which silently reads the pre-update value).
-- //
-- // Checks:
-- //   1) time_stamp = 0 while rst_n is held low
-- //   2) after release, counter increments by exactly 1 every clock, matching the
-- //      golden reference model
-- //   3) a synchronous reset asserted mid-count snaps the counter back to 0 on the
-- //      next rising edge, and counting resumes correctly from 0 afterwards
-- //   4) the counter wraps from all-ones back to 0 (8-bit instance: 0xFF -> 0x00)
-- //      and continues counting correctly past the wrap
-- //   5) default-width (64-bit) instance free-runs the whole test and is checked
-- //      against its own independent reference count, then reset independently of
-- //      the 8-bit instance to confirm the two are not accidentally coupled
-- //////////////////////////////////////////////////////////////////////////////////
library ieee;
use ieee.std_logic_1164.all;
use ieee.numeric_std.all;

entity tb_timestamping_unit is
end entity tb_timestamping_unit;

architecture sim of tb_timestamping_unit is

    constant CLK_PERIOD : time := 10 ns;  -- 100 MHz

    -- DUT #1 -- narrow width, used for the bulk of the checks incl. wrap-around
    constant W8 : natural := 8;
    signal clk         : std_logic := '0';
    signal rst_n       : std_logic := '0';
    signal time_stamp8 : std_logic_vector(W8 - 1 downto 0);

    -- DUT #2 -- default width (64), just to confirm the real configuration works
    constant W64 : natural := 64;
    signal rst_n64      : std_logic := '0';
    signal time_stamp64 : std_logic_vector(W64 - 1 downto 0);

    -- Golden reference model, updated by the tick() procedure below
    signal expected8   : unsigned(W8 - 1 downto 0)  := (others => '0');
    signal expected64  : unsigned(W64 - 1 downto 0) := (others => '0');

    signal checks_run    : natural := 0;
    signal checks_passed : natural := 0;

begin

    -- DUT #1: 8-bit instance, drives most of the testing (incl. wrap-around)
    dut8 : entity work.timestamping_unit
        generic map (
            TIMESTAMP_WIDTH => W8
        )
        port map (
            clk        => clk,
            rst_n      => rst_n,
            time_stamp => time_stamp8
        );

    -- DUT #2: default-width instance (matches real design usage, 64 bits)
    dut64 : entity work.timestamping_unit
        generic map (
            TIMESTAMP_WIDTH => W64
        )
        port map (
            clk        => clk,
            rst_n      => rst_n64,
            time_stamp => time_stamp64
        );

    -- Clock generation (shared by both DUTs)
    clk_gen_p : process
    begin
        clk <= '0';
        wait for CLK_PERIOD / 2;
        clk <= '1';
        wait for CLK_PERIOD / 2;
    end process clk_gen_p;

    stim : process
        variable checks_run_v    : natural := 0;
        variable checks_passed_v : natural := 0;

        procedure check(constant cond : boolean; constant msg : string) is
        begin
            checks_run_v := checks_run_v + 1;
            if cond then
                checks_passed_v := checks_passed_v + 1;
                report "PASS: " & msg;
            else
                report "FAIL: " & msg severity error;
            end if;
            checks_run    <= checks_run_v;
            checks_passed <= checks_passed_v;
        end procedure;

        -- Advances one clock, updates the golden reference model to mirror
        -- exactly what the DUTs themselves should do (sync reset / increment),
        -- then settles 1ns past the edge so signal reads see the update.
        procedure tick is
        begin
            wait until rising_edge(clk);
            if rst_n = '0' then
                expected8 <= (others => '0');
            else
                expected8 <= expected8 + 1;
            end if;

            if rst_n64 = '0' then
                expected64 <= (others => '0');
            else
                expected64 <= expected64 + 1;
            end if;
            wait for 1 ns;
        end procedure;

    begin
        report "==== timestamping_unit testbench start ====";

        ------------------------------------------------------------------
        -- 1) Reset held: time_stamp must stay at 0
        ------------------------------------------------------------------
        rst_n   <= '0';
        rst_n64 <= '0';
        tick;
        check(unsigned(time_stamp8) = 0, "time_stamp8 = 0 while rst_n held low");

        for i in 0 to 4 loop
            tick;
            check(unsigned(time_stamp8) = 0,
                  "time_stamp8 stays 0 during extended reset, cycle " & integer'image(i));
        end loop;

        ------------------------------------------------------------------
        -- 2) Release reset, counter increments by 1 every clock
        ------------------------------------------------------------------
        rst_n   <= '1';
        rst_n64 <= '1';

        for i in 1 to 20 loop
            tick;
            check(unsigned(time_stamp8) = expected8,
                  "time_stamp8 increments correctly, tick " & integer'image(i) &
                  " (got " & integer'image(to_integer(unsigned(time_stamp8))) &
                  ", expected " & integer'image(to_integer(expected8)) & ")");
        end loop;

        ------------------------------------------------------------------
        -- 3) Mid-count synchronous reset: snaps back to 0, then resumes counting
        ------------------------------------------------------------------
        rst_n <= '0';
        tick;
        check(unsigned(time_stamp8) = 0, "time_stamp8 snaps to 0 on synchronous reset mid-count");

        rst_n <= '1';
        for i in 1 to 5 loop
            tick;
            check(unsigned(time_stamp8) = expected8,
                  "time_stamp8 resumes counting correctly after reset, tick " & integer'image(i));
        end loop;

        ------------------------------------------------------------------
        -- 4) Wrap-around: run the 8-bit counter all the way to 0xFF and past it
        --    (fixed iteration count computed from the known current value --
        --    avoids reading a signal in the same delta cycle as its own update)
        ------------------------------------------------------------------
        while expected8 /= to_unsigned(255, W8) loop
            tick;
        end loop;
        check(unsigned(time_stamp8) = 255, "time_stamp8 reaches 0xFF just before wrap");

        tick;  -- one more increment: 255 + 1 wraps to 0
        check(unsigned(time_stamp8) = 0, "time_stamp8 wraps from 0xFF back to 0x00");

        for i in 1 to 5 loop
            tick;
            check(unsigned(time_stamp8) = expected8,
                  "time_stamp8 continues counting correctly after wrap, tick " & integer'image(i));
        end loop;

        ------------------------------------------------------------------
        -- 5) Default-width (64-bit) instance: it's been free-running (in step
        --    with the golden model) the whole test -- confirm it matches
        ------------------------------------------------------------------
        check(unsigned(time_stamp64) = expected64,
              "time_stamp64 (default TIMESTAMP_WIDTH=64) matches expected count " &
              "(got " & integer'image(to_integer(unsigned(time_stamp64))) &
              ", expected " & integer'image(to_integer(expected64)) & ")");

        -- reset the 64-bit instance on its own and confirm it responds independently
        rst_n64 <= '0';
        tick;
        check(unsigned(time_stamp64) = 0, "time_stamp64 resets to 0 independently of the 8-bit instance");
        check(unsigned(time_stamp8) /= 0, "time_stamp8 unaffected by resetting the independent 64-bit instance");

        ------------------------------------------------------------------
        -- Summary
        ------------------------------------------------------------------
        report "==== timestamping_unit testbench done: " &
               integer'image(checks_passed_v) & " / " & integer'image(checks_run_v) &
               " checks passed ====";

        if checks_passed_v = checks_run_v then
            report "ALL CHECKS PASSED";
        else
            report "SOME CHECKS FAILED" severity error;
        end if;

        std.env.stop;
    end process stim;

end architecture sim;

FPGA/IP_repo/timestamping_unit/sim/wave.vcd
$date
  Tue Aug 18 17:21:20 2026
$end
$version
  GHDL v0
$end
$timescale
  1 fs
$end
$scope module standard $end
$upscope $end
$scope module textio $end
$upscope $end
$scope module std_logic_1164 $end
$upscope $end
$scope module numeric_std $end
$upscope $end
$scope module env $end
$upscope $end
$scope module tb_timestamping_unit $end
$var reg 1 ! clk $end
$var reg 1 " rst_n $end
$var reg 8 # time_stamp8[7:0] $end
$var reg 1 $ rst_n64 $end
$var reg 64 % time_stamp64[63:0] $end
$var reg 8 & expected8[7:0] $end
$var reg 64 ' expected64[63:0] $end
$var integer 32 ( checks_run $end
$var integer 32 ) checks_passed $end
$scope module dut8 $end
$var reg 1 * clk $end
$var reg 1 + rst_n $end
$var reg 8 , time_stamp[7:0] $end
$var reg 8 - counter[7:0] $end
$upscope $end
$scope module dut64 $end
$var reg 1 . clk $end
$var reg 1 / rst_n $end
$var reg 64 0 time_stamp[63:0] $end
$var reg 64 1 counter[63:0] $end
$upscope $end
$upscope $end
$enddefinitions $end
#0
0!
0"
b00000000 #
0$
b0000000000000000000000000000000000000000000000000000000000000000 %
b00000000 &
b0000000000000000000000000000000000000000000000000000000000000000 '
b0 (
b0 )
0*
0+
b00000000 ,
b00000000 -
0.
0/
b0000000000000000000000000000000000000000000000000000000000000000 0
b0000000000000000000000000000000000000000000000000000000000000000 1
#5000000
1!
1*
1.
#6000000
b1 (
b1 )
#10000000
0!
0*
0.
#15000000
1!
1*
1.
#16000000
b10 (
b10 )
#20000000
0!
0*
0.
#25000000
1!
1*
1.
#26000000
b11 (
b11 )
#30000000
0!
0*
0.
#35000000
1!
1*
1.
#36000000
b100 (
b100 )
#40000000
0!
0*
0.
#45000000
1!
1*
1.
#46000000
b101 (
b101 )
#50000000
0!
0*
0.
#55000000
1!
1*
1.
#56000000
1"
1$
b110 (
b110 )
1+
1/
#60000000
0!
0*
0.
#65000000
1!
b00000001 #
b0000000000000000000000000000000000000000000000000000000000000001 %
b00000001 &
b0000000000000000000000000000000000000000000000000000000000000001 '
1*
b00000001 ,
b00000001 -
1.
b0000000000000000000000000000000000000000000000000000000000000001 0
b0000000000000000000000000000000000000000000000000000000000000001 1
#66000000
b111 (
b111 )
#70000000
0!
0*
0.
#75000000
1!
b00000010 #
b0000000000000000000000000000000000000000000000000000000000000010 %
b00000010 &
b0000000000000000000000000000000000000000000000000000000000000010 '
1*
b00000010 ,
b00000010 -
1.
b0000000000000000000000000000000000000000000000000000000000000010 0
b0000000000000000000000000000000000000000000000000000000000000010 1
#76000000
b1000 (
b1000 )
#80000000
0!
0*
0.
#85000000
1!
b00000011 #
b0000000000000000000000000000000000000000000000000000000000000011 %
b00000011 &
b0000000000000000000000000000000000000000000000000000000000000011 '
1*
b00000011 ,
b00000011 -
1.
b0000000000000000000000000000000000000000000000000000000000000011 0
b0000000000000000000000000000000000000000000000000000000000000011 1
#86000000
b1001 (
b1001 )
#90000000
0!
0*
0.
#95000000
1!
b00000100 #
b0000000000000000000000000000000000000000000000000000000000000100 %
b00000100 &
b0000000000000000000000000000000000000000000000000000000000000100 '
1*
b00000100 ,
b00000100 -
1.
b0000000000000000000000000000000000000000000000000000000000000100 0
b0000000000000000000000000000000000000000000000000000000000000100 1
#96000000
b1010 (
b1010 )
#100000000
0!
0*
0.
#105000000
1!
b00000101 #
b0000000000000000000000000000000000000000000000000000000000000101 %
b00000101 &
b0000000000000000000000000000000000000000000000000000000000000101 '
1*
b00000101 ,
b00000101 -
1.
b0000000000000000000000000000000000000000000000000000000000000101 0
b0000000000000000000000000000000000000000000000000000000000000101 1
#106000000
b1011 (
b1011 )
#110000000
0!
0*
0.
#115000000
1!
b00000110 #
b0000000000000000000000000000000000000000000000000000000000000110 %
b00000110 &
b0000000000000000000000000000000000000000000000000000000000000110 '
1*
b00000110 ,
b00000110 -
1.
b0000000000000000000000000000000000000000000000000000000000000110 0
b0000000000000000000000000000000000000000000000000000000000000110 1
#116000000
b1100 (
b1100 )
#120000000
0!
0*
0.
#125000000
1!
b00000111 #
b0000000000000000000000000000000000000000000000000000000000000111 %
b00000111 &
b0000000000000000000000000000000000000000000000000000000000000111 '
1*
b00000111 ,
b00000111 -
1.
b0000000000000000000000000000000000000000000000000000000000000111 0
b0000000000000000000000000000000000000000000000000000000000000111 1
#126000000
b1101 (
b1101 )
#130000000
0!
0*
0.
#135000000
1!
b00001000 #
b0000000000000000000000000000000000000000000000000000000000001000 %
b00001000 &
b0000000000000000000000000000000000000000000000000000000000001000 '
1*
b00001000 ,
b00001000 -
1.
b0000000000000000000000000000000000000000000000000000000000001000 0
b0000000000000000000000000000000000000000000000000000000000001000 1
#136000000
b1110 (
b1110 )
#140000000
0!
0*
0.
#145000000
1!
b00001001 #
b0000000000000000000000000000000000000000000000000000000000001001 %
b00001001 &
b0000000000000000000000000000000000000000000000000000000000001001 '
1*
b00001001 ,
b00001001 -
1.
b0000000000000000000000000000000000000000000000000000000000001001 0
b0000000000000000000000000000000000000000000000000000000000001001 1
#146000000
b1111 (
b1111 )
#150000000
0!
0*
0.
#155000000
1!
b00001010 #
b0000000000000000000000000000000000000000000000000000000000001010 %
b00001010 &
b0000000000000000000000000000000000000000000000000000000000001010 '
1*
b00001010 ,
b00001010 -
1.
b0000000000000000000000000000000000000000000000000000000000001010 0
b0000000000000000000000000000000000000000000000000000000000001010 1
#156000000
b10000 (
b10000 )
#160000000
0!
0*
0.
#165000000
1!
b00001011 #
b0000000000000000000000000000000000000000000000000000000000001011 %
b00001011 &
b0000000000000000000000000000000000000000000000000000000000001011 '
1*
b00001011 ,
b00001011 -
1.
b0000000000000000000000000000000000000000000000000000000000001011 0
b0000000000000000000000000000000000000000000000000000000000001011 1
#166000000
b10001 (
b10001 )
#170000000
0!
0*
0.
#175000000
1!
b00001100 #
b0000000000000000000000000000000000000000000000000000000000001100 %
b00001100 &
b0000000000000000000000000000000000000000000000000000000000001100 '
1*
b00001100 ,
b00001100 -
1.
b0000000000000000000000000000000000000000000000000000000000001100 0
b0000000000000000000000000000000000000000000000000000000000001100 1
#176000000
b10010 (
b10010 )
#180000000
0!
0*
0.
#185000000
1!
b00001101 #
b0000000000000000000000000000000000000000000000000000000000001101 %
b00001101 &
b0000000000000000000000000000000000000000000000000000000000001101 '
1*
b00001101 ,
b00001101 -
1.
b0000000000000000000000000000000000000000000000000000000000001101 0
b0000000000000000000000000000000000000000000000000000000000001101 1
#186000000
b10011 (
b10011 )
#190000000
0!
0*
0.
#195000000
1!
b00001110 #
b0000000000000000000000000000000000000000000000000000000000001110 %
b00001110 &
b0000000000000000000000000000000000000000000000000000000000001110 '
1*
b00001110 ,
b00001110 -
1.
b0000000000000000000000000000000000000000000000000000000000001110 0
b0000000000000000000000000000000000000000000000000000000000001110 1
#196000000
b10100 (
b10100 )
#200000000
0!
0*
0.
#205000000
1!
b00001111 #
b0000000000000000000000000000000000000000000000000000000000001111 %
b00001111 &
b0000000000000000000000000000000000000000000000000000000000001111 '
1*
b00001111 ,
b00001111 -
1.
b0000000000000000000000000000000000000000000000000000000000001111 0
b0000000000000000000000000000000000000000000000000000000000001111 1
#206000000
b10101 (
b10101 )
#210000000
0!
0*
0.
#215000000
1!
b00010000 #
b0000000000000000000000000000000000000000000000000000000000010000 %
b00010000 &
b0000000000000000000000000000000000000000000000000000000000010000 '
1*
b00010000 ,
b00010000 -
1.
b0000000000000000000000000000000000000000000000000000000000010000 0
b0000000000000000000000000000000000000000000000000000000000010000 1
#216000000
b10110 (
b10110 )
#220000000
0!
0*
0.
#225000000
1!
b00010001 #
b0000000000000000000000000000000000000000000000000000000000010001 %
b00010001 &
b0000000000000000000000000000000000000000000000000000000000010001 '
1*
b00010001 ,
b00010001 -
1.
b0000000000000000000000000000000000000000000000000000000000010001 0
b0000000000000000000000000000000000000000000000000000000000010001 1
#226000000
b10111 (
b10111 )
#230000000
0!
0*
0.
#235000000
1!
b00010010 #
b0000000000000000000000000000000000000000000000000000000000010010 %
b00010010 &
b0000000000000000000000000000000000000000000000000000000000010010 '
1*
b00010010 ,
b00010010 -
1.
b0000000000000000000000000000000000000000000000000000000000010010 0
b0000000000000000000000000000000000000000000000000000000000010010 1
#236000000
b11000 (
b11000 )
#240000000
0!
0*
0.
#245000000
1!
b00010011 #
b0000000000000000000000000000000000000000000000000000000000010011 %
b00010011 &
b0000000000000000000000000000000000000000000000000000000000010011 '
1*
b00010011 ,
b00010011 -
1.
b0000000000000000000000000000000000000000000000000000000000010011 0
b0000000000000000000000000000000000000000000000000000000000010011 1
#246000000
b11001 (
b11001 )
#250000000
0!
0*
0.
#255000000
1!
b00010100 #
b0000000000000000000000000000000000000000000000000000000000010100 %
b00010100 &
b0000000000000000000000000000000000000000000000000000000000010100 '
1*
b00010100 ,
b00010100 -
1.
b0000000000000000000000000000000000000000000000000000000000010100 0
b0000000000000000000000000000000000000000000000000000000000010100 1
#256000000
0"
b11010 (
b11010 )
0+
#260000000
0!
0*
0.
#265000000
1!
b00000000 #
b0000000000000000000000000000000000000000000000000000000000010101 %
b00000000 &
b0000000000000000000000000000000000000000000000000000000000010101 '
1*
b00000000 ,
b00000000 -
1.
b0000000000000000000000000000000000000000000000000000000000010101 0
b0000000000000000000000000000000000000000000000000000000000010101 1
#266000000
1"
b11011 (
b11011 )
1+
#270000000
0!
0*
0.
#275000000
1!
b00000001 #
b0000000000000000000000000000000000000000000000000000000000010110 %
b00000001 &
b0000000000000000000000000000000000000000000000000000000000010110 '
1*
b00000001 ,
b00000001 -
1.
b0000000000000000000000000000000000000000000000000000000000010110 0
b0000000000000000000000000000000000000000000000000000000000010110 1
#276000000
b11100 (
b11100 )
#280000000
0!
0*
0.
#285000000
1!
b00000010 #
b0000000000000000000000000000000000000000000000000000000000010111 %
b00000010 &
b0000000000000000000000000000000000000000000000000000000000010111 '
1*
b00000010 ,
b00000010 -
1.
b0000000000000000000000000000000000000000000000000000000000010111 0
b0000000000000000000000000000000000000000000000000000000000010111 1
#286000000
b11101 (
b11101 )
#290000000
0!
0*
0.
#295000000
1!
b00000011 #
b0000000000000000000000000000000000000000000000000000000000011000 %
b00000011 &
b0000000000000000000000000000000000000000000000000000000000011000 '
1*
b00000011 ,
b00000011 -
1.
b0000000000000000000000000000000000000000000000000000000000011000 0
b0000000000000000000000000000000000000000000000000000000000011000 1
#296000000
b11110 (
b11110 )
#300000000
0!
0*
0.
#305000000
1!
b00000100 #
b0000000000000000000000000000000000000000000000000000000000011001 %
b00000100 &
b0000000000000000000000000000000000000000000000000000000000011001 '
1*
b00000100 ,
b00000100 -
1.
b0000000000000000000000000000000000000000000000000000000000011001 0
b0000000000000000000000000000000000000000000000000000000000011001 1
#306000000
b11111 (
b11111 )
#310000000
0!
0*
0.
#315000000
1!
b00000101 #
b0000000000000000000000000000000000000000000000000000000000011010 %
b00000101 &
b0000000000000000000000000000000000000000000000000000000000011010 '
1*
b00000101 ,
b00000101 -
1.
b0000000000000000000000000000000000000000000000000000000000011010 0
b0000000000000000000000000000000000000000000000000000000000011010 1
#316000000
b100000 (
b100000 )
#320000000
0!
0*
0.
#325000000
1!
b00000110 #
b0000000000000000000000000000000000000000000000000000000000011011 %
b00000110 &
b0000000000000000000000000000000000000000000000000000000000011011 '
1*
b00000110 ,
b00000110 -
1.
b0000000000000000000000000000000000000000000000000000000000011011 0
b0000000000000000000000000000000000000000000000000000000000011011 1
#330000000
0!
0*
0.
#335000000
1!
b00000111 #
b0000000000000000000000000000000000000000000000000000000000011100 %
b00000111 &
b0000000000000000000000000000000000000000000000000000000000011100 '
1*
b00000111 ,
b00000111 -
1.
b0000000000000000000000000000000000000000000000000000000000011100 0
b0000000000000000000000000000000000000000000000000000000000011100 1
#340000000
0!
0*
0.
#345000000
1!
b00001000 #
b0000000000000000000000000000000000000000000000000000000000011101 %
b00001000 &
b0000000000000000000000000000000000000000000000000000000000011101 '
1*
b00001000 ,
b00001000 -
1.
b0000000000000000000000000000000000000000000000000000000000011101 0
b0000000000000000000000000000000000000000000000000000000000011101 1
#350000000
0!
0*
0.
#355000000
1!
b00001001 #
b0000000000000000000000000000000000000000000000000000000000011110 %
b00001001 &
b0000000000000000000000000000000000000000000000000000000000011110 '
1*
b00001001 ,
b00001001 -
1.
b0000000000000000000000000000000000000000000000000000000000011110 0
b0000000000000000000000000000000000000000000000000000000000011110 1
#360000000
0!
0*
0.
#365000000
1!
b00001010 #
b0000000000000000000000000000000000000000000000000000000000011111 %
b00001010 &
b0000000000000000000000000000000000000000000000000000000000011111 '
1*
b00001010 ,
b00001010 -
1.
b0000000000000000000000000000000000000000000000000000000000011111 0
b0000000000000000000000000000000000000000000000000000000000011111 1
#370000000
0!
0*
0.
#375000000
1!
b00001011 #
b0000000000000000000000000000000000000000000000000000000000100000 %
b00001011 &
b0000000000000000000000000000000000000000000000000000000000100000 '
1*
b00001011 ,
b00001011 -
1.
b0000000000000000000000000000000000000000000000000000000000100000 0
b0000000000000000000000000000000000000000000000000000000000100000 1
#380000000
0!
0*
0.
#385000000
1!
b00001100 #
b0000000000000000000000000000000000000000000000000000000000100001 %
b00001100 &
b0000000000000000000000000000000000000000000000000000000000100001 '
1*
b00001100 ,
b00001100 -
1.
b0000000000000000000000000000000000000000000000000000000000100001 0
b0000000000000000000000000000000000000000000000000000000000100001 1
#390000000
0!
0*
0.
#395000000
1!
b00001101 #
b0000000000000000000000000000000000000000000000000000000000100010 %
b00001101 &
b0000000000000000000000000000000000000000000000000000000000100010 '
1*
b00001101 ,
b00001101 -
1.
b0000000000000000000000000000000000000000000000000000000000100010 0
b0000000000000000000000000000000000000000000000000000000000100010 1
#400000000
0!
0*
0.
#405000000
1!
b00001110 #
b0000000000000000000000000000000000000000000000000000000000100011 %
b00001110 &
b0000000000000000000000000000000000000000000000000000000000100011 '
1*
b00001110 ,
b00001110 -
1.
b0000000000000000000000000000000000000000000000000000000000100011 0
b0000000000000000000000000000000000000000000000000000000000100011 1
#410000000
0!
0*
0.
#415000000
1!
b00001111 #
b0000000000000000000000000000000000000000000000000000000000100100 %
b00001111 &
b0000000000000000000000000000000000000000000000000000000000100100 '
1*
b00001111 ,
b00001111 -
1.
b0000000000000000000000000000000000000000000000000000000000100100 0
b0000000000000000000000000000000000000000000000000000000000100100 1
#420000000
0!
0*
0.
#425000000
1!
b00010000 #
b0000000000000000000000000000000000000000000000000000000000100101 %
b00010000 &
b0000000000000000000000000000000000000000000000000000000000100101 '
1*
b00010000 ,
b00010000 -
1.
b0000000000000000000000000000000000000000000000000000000000100101 0
b0000000000000000000000000000000000000000000000000000000000100101 1
#430000000
0!
0*
0.
#435000000
1!
b00010001 #
b0000000000000000000000000000000000000000000000000000000000100110 %
b00010001 &
b0000000000000000000000000000000000000000000000000000000000100110 '
1*
b00010001 ,
b00010001 -
1.
b0000000000000000000000000000000000000000000000000000000000100110 0
b0000000000000000000000000000000000000000000000000000000000100110 1
#440000000
0!
0*
0.
#445000000
1!
b00010010 #
b0000000000000000000000000000000000000000000000000000000000100111 %
b00010010 &
b0000000000000000000000000000000000000000000000000000000000100111 '
1*
b00010010 ,
b00010010 -
1.
b0000000000000000000000000000000000000000000000000000000000100111 0
b0000000000000000000000000000000000000000000000000000000000100111 1
#450000000
0!
0*
0.
#455000000
1!
b00010011 #
b0000000000000000000000000000000000000000000000000000000000101000 %
b00010011 &
b0000000000000000000000000000000000000000000000000000000000101000 '
1*
b00010011 ,
b00010011 -
1.
b0000000000000000000000000000000000000000000000000000000000101000 0
b0000000000000000000000000000000000000000000000000000000000101000 1
#460000000
0!
0*
0.
#465000000
1!
b00010100 #
b0000000000000000000000000000000000000000000000000000000000101001 %
b00010100 &
b0000000000000000000000000000000000000000000000000000000000101001 '
1*
b00010100 ,
b00010100 -
1.
b0000000000000000000000000000000000000000000000000000000000101001 0
b0000000000000000000000000000000000000000000000000000000000101001 1
#470000000
0!
0*
0.
#475000000
1!
b00010101 #
b0000000000000000000000000000000000000000000000000000000000101010 %
b00010101 &
b0000000000000000000000000000000000000000000000000000000000101010 '
1*
b00010101 ,
b00010101 -
1.
b0000000000000000000000000000000000000000000000000000000000101010 0
b0000000000000000000000000000000000000000000000000000000000101010 1
#480000000
0!
0*
0.
#485000000
1!
b00010110 #
b0000000000000000000000000000000000000000000000000000000000101011 %
b00010110 &
b0000000000000000000000000000000000000000000000000000000000101011 '
1*
b00010110 ,
b00010110 -
1.
b0000000000000000000000000000000000000000000000000000000000101011 0
b0000000000000000000000000000000000000000000000000000000000101011 1
#490000000
0!
0*
0.
#495000000
1!
b00010111 #
b0000000000000000000000000000000000000000000000000000000000101100 %
b00010111 &
b0000000000000000000000000000000000000000000000000000000000101100 '
1*
b00010111 ,
b00010111 -
1.
b0000000000000000000000000000000000000000000000000000000000101100 0
b0000000000000000000000000000000000000000000000000000000000101100 1
#500000000
0!
0*
0.
#505000000
1!
b00011000 #
b0000000000000000000000000000000000000000000000000000000000101101 %
b00011000 &
b0000000000000000000000000000000000000000000000000000000000101101 '
1*
b00011000 ,
b00011000 -
1.
b0000000000000000000000000000000000000000000000000000000000101101 0
b0000000000000000000000000000000000000000000000000000000000101101 1
#510000000
0!
0*
0.
#515000000
1!
b00011001 #
b0000000000000000000000000000000000000000000000000000000000101110 %
b00011001 &
b0000000000000000000000000000000000000000000000000000000000101110 '
1*
b00011001 ,
b00011001 -
1.
b0000000000000000000000000000000000000000000000000000000000101110 0
b0000000000000000000000000000000000000000000000000000000000101110 1
#520000000
0!
0*
0.
#525000000
1!
b00011010 #
b0000000000000000000000000000000000000000000000000000000000101111 %
b00011010 &
b0000000000000000000000000000000000000000000000000000000000101111 '
1*
b00011010 ,
b00011010 -
1.
b0000000000000000000000000000000000000000000000000000000000101111 0
b0000000000000000000000000000000000000000000000000000000000101111 1
#530000000
0!
0*
0.
#535000000
1!
b00011011 #
b0000000000000000000000000000000000000000000000000000000000110000 %
b00011011 &
b0000000000000000000000000000000000000000000000000000000000110000 '
1*
b00011011 ,
b00011011 -
1.
b0000000000000000000000000000000000000000000000000000000000110000 0
b0000000000000000000000000000000000000000000000000000000000110000 1
#540000000
0!
0*
0.
#545000000
1!
b00011100 #
b0000000000000000000000000000000000000000000000000000000000110001 %
b00011100 &
b0000000000000000000000000000000000000000000000000000000000110001 '
1*
b00011100 ,
b00011100 -
1.
b0000000000000000000000000000000000000000000000000000000000110001 0
b0000000000000000000000000000000000000000000000000000000000110001 1
#550000000
0!
0*
0.
#555000000
1!
b00011101 #
b0000000000000000000000000000000000000000000000000000000000110010 %
b00011101 &
b0000000000000000000000000000000000000000000000000000000000110010 '
1*
b00011101 ,
b00011101 -
1.
b0000000000000000000000000000000000000000000000000000000000110010 0
b0000000000000000000000000000000000000000000000000000000000110010 1
#560000000
0!
0*
0.
#565000000
1!
b00011110 #
b0000000000000000000000000000000000000000000000000000000000110011 %
b00011110 &
b0000000000000000000000000000000000000000000000000000000000110011 '
1*
b00011110 ,
b00011110 -
1.
b0000000000000000000000000000000000000000000000000000000000110011 0
b0000000000000000000000000000000000000000000000000000000000110011 1
#570000000
0!
0*
0.
#575000000
1!
b00011111 #
b0000000000000000000000000000000000000000000000000000000000110100 %
b00011111 &
b0000000000000000000000000000000000000000000000000000000000110100 '
1*
b00011111 ,
b00011111 -
1.
b0000000000000000000000000000000000000000000000000000000000110100 0
b0000000000000000000000000000000000000000000000000000000000110100 1
#580000000
0!
0*
0.
#585000000
1!
b00100000 #
b0000000000000000000000000000000000000000000000000000000000110101 %
b00100000 &
b0000000000000000000000000000000000000000000000000000000000110101 '
1*
b00100000 ,
b00100000 -
1.
b0000000000000000000000000000000000000000000000000000000000110101 0
b0000000000000000000000000000000000000000000000000000000000110101 1
#590000000
0!
0*
0.
#595000000
1!
b00100001 #
b0000000000000000000000000000000000000000000000000000000000110110 %
b00100001 &
b0000000000000000000000000000000000000000000000000000000000110110 '
1*
b00100001 ,
b00100001 -
1.
b0000000000000000000000000000000000000000000000000000000000110110 0
b0000000000000000000000000000000000000000000000000000000000110110 1
#600000000
0!
0*
0.
#605000000
1!
b00100010 #
b0000000000000000000000000000000000000000000000000000000000110111 %
b00100010 &
b0000000000000000000000000000000000000000000000000000000000110111 '
1*
b00100010 ,
b00100010 -
1.
b0000000000000000000000000000000000000000000000000000000000110111 0
b0000000000000000000000000000000000000000000000000000000000110111 1
#610000000
0!
0*
0.
#615000000
1!
b00100011 #
b0000000000000000000000000000000000000000000000000000000000111000 %
b00100011 &
b0000000000000000000000000000000000000000000000000000000000111000 '
1*
b00100011 ,
b00100011 -
1.
b0000000000000000000000000000000000000000000000000000000000111000 0
b0000000000000000000000000000000000000000000000000000000000111000 1
#620000000
0!
0*
0.
#625000000
1!
b00100100 #
b0000000000000000000000000000000000000000000000000000000000111001 %
b00100100 &
b0000000000000000000000000000000000000000000000000000000000111001 '
1*
b00100100 ,
b00100100 -
1.
b0000000000000000000000000000000000000000000000000000000000111001 0
b0000000000000000000000000000000000000000000000000000000000111001 1
#630000000
0!
0*
0.
#635000000
1!
b00100101 #
b0000000000000000000000000000000000000000000000000000000000111010 %
b00100101 &
b0000000000000000000000000000000000000000000000000000000000111010 '
1*
b00100101 ,
b00100101 -
1.
b0000000000000000000000000000000000000000000000000000000000111010 0
b0000000000000000000000000000000000000000000000000000000000111010 1
#640000000
0!
0*
0.
