FPGA/IP_repo/UART_CONTROLLER/src/UART_CONTROLLER.vhd
-- //////////////////////////////////////////////////////////////////////////////////
-- // Engineer: Abdelrahman Hewala (Shiro)
-- //
-- // Design Name: ce_pulse_gen
-- // Project Name: EKF with HLS
-- // Target Devices: Xilinx Basys 3
-- // Tool Versions: Vivado 2026.1
-- //
-- // Description:
-- //   This is a UART controller module. its main purpsoe is to read the data from
-- //   Axis fifo and sequence the data in form of a frame and provides a CHK test.
-- //   The controller Burst the data to an axis serilizer as the word is 16 bits not 8.
-- //   then the serilizer sends the data to the UART IP. all using axis protocol. 
-- //
-- // UART Controller Modes:
-- // the UART controller has two modes:
-- //   1) Mode 0 => will read the ICM data directly from Axis FIFO and bypass the EKF
-- //   2) Mode 1 => will read beside the input data + kalman filter outputs
-- //
-- // Frame layout:
-- //   1) SYNC1 & SYNC2  => both 1 word
-- //   2) MODE and LEN => both 1 word
-- //   3) PAYLOAD
-- //   4) CHK
-- // 
-- // Mode 1 payload  layout (15 words)
-- //   1) time stamp 4 words
-- //   2) accx       1 word
-- //   3) accy       1 word
-- //   4) accz       1 word
-- //   5) gyrox      1 word
-- //   6) gyroy      1 word
-- //   7) gyroz      1 word
-- //   8) temp       1 word
-- //   9) magx       1 word
-- //   10) magy      1 word
-- //   11) magz      1 word
-- //   12) status    1 word
-- //
-- // CHK is a simple XOR for each word sent. 
-- //
-- // Revision 0.01 - File Created
-- // VHDL Version: VHDL-2008
-- //////////////////////////////////////////////////////////////////////////////////

library ieee;
use ieee.std_logic_1164.all;

entity UART_CONTROLLER is
    generic (
        MODE : natural := 0                -- O = bypass filter, 1 or other : add the filter -- can be replaced with a switch later
    );
    port (
        clk   : in  std_logic;
        rst_n : in  std_logic;

        -- AXI-Stream input interface (fifo_out)
        s_axis_fifo_tdata  : in  std_logic_vector(15 downto 0);
        s_axis_fifo_tvalid : in  std_logic;
        s_axis_fifo_tlast  : in  std_logic;
        s_axis_fifo_tready : out std_logic; 


        -- AXI-Stream output (serilizar input)
        m_axis_tdata  : out std_logic_vector(15 downto 0);    
        m_axis_tvalid : out std_logic;
        m_axis_tready : in  std_logic

    );
end entity UART_CONTROLLER;


architecture rtl of UART_CONTROLLER is
-- Constants
    constant SYNC   : std_logic_vector(15 downto 0)  := x"AA55";
    constant MODE_0 :std_logic_vector(15 downto 0)   := x"001E";     -- 00 for mode 0, 1E = 30 bytes
    constant MODE_1 :std_logic_vector(15 downto 0)   := x"012A";     -- 01 for mode 1, 2A = 42 bytes

-- Ports signals 
    signal s_axis_fifo_tready_r : std_logic := '1';

    signal m_axis_tvalid_r      : std_logic := '0';
    signal m_axis_tdata_r       : std_logic_vector(15 downto 0) := (others => '0');


-- Controller FSM
    type state_t is (IDLE, SENDING_SYNC,  SENDING_MODE_LEN, SERILIZER_HANDSHAKE, READ_DATA, SEND_DATA, SEND_CHK);
    
    -- FSM signals
    signal state         : state_t := IDLE;
    signal received_word : std_logic_vector(15 downto 0) := (others => '0');            -- latches the first word
    signal received_word_tlast_reg :std_logic := '0';                                   -- stores last signal for transaction
    signal chk_word      : std_logic_vector(15 downto 0) := (others => '0');            -- holds the Check sum word (XOR)

begin

-- Signal to port Assignation
    s_axis_fifo_tready <= s_axis_fifo_tready_r;

    m_axis_tvalid <= m_axis_tvalid_r;
    m_axis_tdata <= m_axis_tdata_r;

-- Controller FSM (IDLE, SENDING_SYNC,  SENDING_MODE_LEN, SERILIZER_HANDSHAKE, READ_DATA, SEND_DATA, SEND_CHK)
    fsm_p : process(clk)
    begin
        if rising_edge(clk) then
            if rst_n = '0' then
                state <= IDLE;

                s_axis_fifo_tready_r <= '1';
                m_axis_tvalid_r      <= '0';
                m_axis_tdata_r       <=  (others => '0');

                received_word        <=  (others => '0');
                chk_word             <=  (others => '0');
                received_word_tlast_reg <= '0';

            else
                case state is 
                    when IDLE =>
                        if s_axis_fifo_tvalid = '1' and s_axis_fifo_tready_r = '1' then
                            s_axis_fifo_tready_r <= '0';                 -- de asserting ready flag
                            received_word        <= s_axis_fifo_tdata;   -- latching the first word
                            chk_word             <= chk_word XOR s_axis_fifo_tdata;

                            m_axis_tdata_r  <= SYNC;                     -- sending Sync command
                            m_axis_tvalid_r <= '1';
                            state <= SENDING_SYNC;
                        end if;

                    when SENDING_SYNC => 
                        if m_axis_tvalid_r = '1' and m_axis_tready = '1' then  -- serilizar recieve the SYNC word and will be sending it 
                            m_axis_tvalid_r <= '1';

                            if MODE = 0 then
                                m_axis_tdata_r <= MODE_0;
                            else 
                                m_axis_tdata_r <= MODE_1;
                            end if;

                            state <= SENDING_MODE_LEN;
                        end if;

                    when SENDING_MODE_LEN => 
                        if m_axis_tvalid_r = '1' and m_axis_tready = '1' then  -- serilizar recieve the MODE word and will be sending it 
                            m_axis_tvalid_r <= '1';
                            m_axis_tdata_r  <= received_word;                      -- sending the firt word latched in the begining

                            state <= SERILIZER_HANDSHAKE;
                        end if;

                    when SERILIZER_HANDSHAKE =>
                        if m_axis_tvalid_r = '1' and m_axis_tready = '1' then  -- last word is received by the serilizer 
                            state           <= READ_DATA;
                            m_axis_tvalid_r <= '0';        -- De asserting the ready flag;

                            s_axis_fifo_tready_r <= '1';   -- we are ready for receiving a new word from the  fifo;
                        end if;

                    when READ_DATA => 
                        if s_axis_fifo_tvalid = '1' and s_axis_fifo_tready_r = '1' then
                            s_axis_fifo_tready_r    <= '0';                             -- de asserting ready fifo flag - stop receiving

                            m_axis_tdata_r          <= s_axis_fifo_tdata;               -- sending the new word directly  to the serilizer
                            m_axis_tvalid_r         <= '1';                             -- raising ready flag for the serilizer
                            received_word_tlast_reg <= s_axis_fifo_tlast;               -- latching TLAST flag of the received word
                            chk_word                <= chk_word XOR s_axis_fifo_tdata;  -- Updating chk sum. 

                            state <= SEND_DATA;
                        end if;

                    when SEND_DATA => 
                        if m_axis_tvalid_r = '1' and m_axis_tready = '1' then  -- serilizar just recieved the word
                            if received_word_tlast_reg = '1' then              -- if this was the last byte. the pay load is done. send chksum
                                s_axis_fifo_tready_r <= '0';                   -- we are not ready yet to recieve a new word. 
                                m_axis_tdata_r       <= chk_word;                   -- send CHK
                                m_axis_tvalid_r      <= '1'; 
                                state                <= SEND_CHK;
                            else 
                                s_axis_fifo_tready_r <= '1';                        -- asserting ready fifo flag - we are back ready to receive data
                                m_axis_tvalid_r      <= '0';                        -- de-asserting the serilizer valid flag, whatever next is not valid
                                state                <= READ_DATA;
                            end if;
                        end if;

                    when SEND_CHK => 
                        if m_axis_tvalid_r = '1' and m_axis_tready = '1' then  -- serilizar just recieved the last word chk sum
                            m_axis_tvalid_r      <= '0'; 
                            s_axis_fifo_tready_r <= '1';                       -- asserting ready fifo flag - we are back ready to receive data
                            chk_word             <= (others => '0');           -- reseting the chk word for the next cycle
                            state                <= IDLE;
                        end if;
                end case;
            end if;
        end if;

    end process fsm_p;
    
end architecture rtl;

FPGA/IP_repo/UART_CONTROLLER/tb/tb_UART_CONTROLLER.vhd
-- //////////////////////////////////////////////////////////////////////////////////
-- // Engineer: Abdelrahman Hewala (Shiro)
-- //
-- // Design Name: tb_uart_controller
-- // Project Name: EKF with HLS
-- //
-- // Description:
-- //   Self-checking testbench for UART_CONTROLLER (MODE = 0). Drives two
-- //   back-to-back 15-word frames through the AXI-Stream fifo input and checks
-- //   every word of the emitted frame: SYNC, MODE/LEN, all 15 payload echoes,
-- //   and the CHK word. Running two distinct frames back-to-back specifically
-- //   regression-tests that chk_word is not carried over between frames.
-- //
-- // VHDL Version: VHDL-2008
-- //////////////////////////////////////////////////////////////////////////////////
library ieee;
use ieee.std_logic_1164.all;
use std.env.all;

entity tb_uart_controller is
end entity;

architecture sim of tb_uart_controller is

    constant CLK_PERIOD : time := 10 ns;  -- 100 MHz, arbitrary for this logic-only test

    constant MODE_G : natural := 0;

    constant SYNC_WORD     : std_logic_vector(15 downto 0) := x"AA55";
    constant MODE_LEN_WORD : std_logic_vector(15 downto 0) := x"001E";  -- matches MODE_0 for MODE_G = 0

    type payload_array_t is array (0 to 14) of std_logic_vector(15 downto 0);

    -- Two distinct payloads so a stale chk_word carried over from frame 1 into
    -- frame 2 would produce a mismatching CHK and get caught.
    -- Layout: 4 time-stamp words, accx/y/z, gyrox/y/z, temp, magx/y/z, status (15 total).
    constant PAYLOAD1_FULL : payload_array_t := (
        x"0001", x"0002", x"0003", x"0004",
        x"0AA1", x"0AA2", x"0AA3",
        x"0BB1", x"0BB2", x"0BB3",
        x"00C1",
        x"0DD1", x"0DD2", x"0DD3",
        x"00E1"
    );

    constant PAYLOAD2_FULL : payload_array_t := (
        x"1001", x"1002", x"1003", x"1004",
        x"1AA1", x"1AA2", x"1AA3",
        x"1BB1", x"1BB2", x"1BB3",
        x"10C1",
        x"1DD1", x"1DD2", x"1DD3",
        x"10E1"
    );

    signal clk   : std_logic := '0';
    signal rst_n : std_logic := '0';

    signal s_axis_fifo_tdata  : std_logic_vector(15 downto 0) := (others => '0');
    signal s_axis_fifo_tvalid : std_logic := '0';
    signal s_axis_fifo_tlast  : std_logic := '0';
    signal s_axis_fifo_tready : std_logic;

    signal m_axis_tdata  : std_logic_vector(15 downto 0);
    signal m_axis_tvalid : std_logic;
    signal m_axis_tready : std_logic := '1';  -- always-ready sink

    signal sim_done : boolean := false;

    function xor_all(payload : payload_array_t) return std_logic_vector is
        variable result : std_logic_vector(15 downto 0) := (others => '0');
    begin
        for i in payload'range loop
            result := result xor payload(i);
        end loop;
        return result;
    end function;

begin

    ----------------------------------------------------------------
    -- DUT
    ----------------------------------------------------------------
    dut : entity work.UART_CONTROLLER
        generic map (
            MODE => MODE_G
        )
        port map (
            clk                => clk,
            rst_n              => rst_n,
            s_axis_fifo_tdata  => s_axis_fifo_tdata,
            s_axis_fifo_tvalid => s_axis_fifo_tvalid,
            s_axis_fifo_tlast  => s_axis_fifo_tlast,
            s_axis_fifo_tready => s_axis_fifo_tready,
            m_axis_tdata       => m_axis_tdata,
            m_axis_tvalid      => m_axis_tvalid,
            m_axis_tready      => m_axis_tready
        );

    ----------------------------------------------------------------
    -- Clock
    ----------------------------------------------------------------
    clk_p : process
    begin
        while not sim_done loop
            clk <= '0';
            wait for CLK_PERIOD / 2;
            clk <= '1';
            wait for CLK_PERIOD / 2;
        end loop;
        wait;
    end process clk_p;

    ----------------------------------------------------------------
    -- Reset
    ----------------------------------------------------------------
    rst_p : process
    begin
        rst_n <= '0';
        wait for CLK_PERIOD * 5;
        wait until rising_edge(clk);
        rst_n <= '1';
        wait;
    end process rst_p;

    ----------------------------------------------------------------
    -- Driver + checker: send two frames back-to-back, verify every word
    ----------------------------------------------------------------
    test_p : process
        variable payload   : payload_array_t;
        variable exp_chk    : std_logic_vector(15 downto 0);
        variable fail_count : natural := 0;
    begin
        wait until rst_n = '1';
        wait until rising_edge(clk);

        for frame in 0 to 1 loop

            if frame = 0 then
                payload := PAYLOAD1_FULL;
            else
                payload := PAYLOAD2_FULL;
            end if;
            exp_chk := xor_all(payload);

            -- send payload word 0 (latched internally, forwarded after MODE/LEN)
            s_axis_fifo_tdata  <= payload(0);
            s_axis_fifo_tvalid <= '1';
            s_axis_fifo_tlast  <= '0';
            wait until rising_edge(clk) and s_axis_fifo_tready = '1';
            s_axis_fifo_tvalid <= '0';

            -- expect SYNC
            wait until rising_edge(clk) and m_axis_tvalid = '1';
            if m_axis_tdata /= SYNC_WORD then
                report "FAIL frame " & integer'image(frame) & ": SYNC mismatch, got 0x" &
                       to_hstring(m_axis_tdata) severity error;
                fail_count := fail_count + 1;
            end if;

            -- expect MODE/LEN
            wait until rising_edge(clk) and m_axis_tvalid = '1';
            if m_axis_tdata /= MODE_LEN_WORD then
                report "FAIL frame " & integer'image(frame) & ": MODE/LEN mismatch, got 0x" &
                       to_hstring(m_axis_tdata) severity error;
                fail_count := fail_count + 1;
            end if;

            -- expect echoed payload word 0
            wait until rising_edge(clk) and m_axis_tvalid = '1';
            if m_axis_tdata /= payload(0) then
                report "FAIL frame " & integer'image(frame) & ": payload[0] mismatch, got 0x" &
                       to_hstring(m_axis_tdata) severity error;
                fail_count := fail_count + 1;
            end if;

            -- send + check payload words 1..14
            for i in 1 to 14 loop
                s_axis_fifo_tdata  <= payload(i);
                s_axis_fifo_tvalid <= '1';
                if i = 14 then
                    s_axis_fifo_tlast <= '1';
                else
                    s_axis_fifo_tlast <= '0';
                end if;
                wait until rising_edge(clk) and s_axis_fifo_tready = '1';
                s_axis_fifo_tvalid <= '0';
                s_axis_fifo_tlast  <= '0';

                wait until rising_edge(clk) and m_axis_tvalid = '1';
                if m_axis_tdata /= payload(i) then
                    report "FAIL frame " & integer'image(frame) & ": payload[" &
                           integer'image(i) & "] mismatch, got 0x" & to_hstring(m_axis_tdata) &
                           " expected 0x" & to_hstring(payload(i)) severity error;
                    fail_count := fail_count + 1;
                end if;
            end loop;

            -- expect CHK
            wait until rising_edge(clk) and m_axis_tvalid = '1';
            if m_axis_tdata /= exp_chk then
                report "FAIL frame " & integer'image(frame) & ": CHK mismatch, got 0x" &
                       to_hstring(m_axis_tdata) & " expected 0x" & to_hstring(exp_chk) severity error;
                fail_count := fail_count + 1;
            else
                report "PASS frame " & integer'image(frame) & ": CHK correct (0x" &
                       to_hstring(exp_chk) & ")" severity note;
            end if;

        end loop;

        if fail_count = 0 then
            report "PASS: all frames received correctly, no mismatches" severity note;
        else
            report "FAIL: " & integer'image(fail_count) & " mismatch(es) detected" severity error;
        end if;

        sim_done <= true;
        wait for CLK_PERIOD * 2;
        std.env.finish;
    end process test_p;

    ----------------------------------------------------------------
    -- Watchdog
    ----------------------------------------------------------------
    watchdog_p : process
    begin
        wait for CLK_PERIOD * 2000;
        if not sim_done then
            report "FAIL: watchdog timeout, DUT stalled" severity failure;
        end if;
        wait;
    end process watchdog_p;

end architecture sim;

FPGA/IP_repo/UART_CONTROLLER/sim/wave.vcd
$date
  Tue Aug 18 20:08:47 2026
$end
$version
  GHDL v0
$end
$timescale
  1 fs
$end
$scope module standard $end
$upscope $end
$scope module textio $end
$upscope $end
$scope module std_logic_1164 $end
$upscope $end
$scope module env $end
$upscope $end
$scope module tb_uart_controller $end
$var reg 1 ! clk $end
$var reg 1 " rst_n $end
$var reg 16 # s_axis_fifo_tdata[15:0] $end
$var reg 1 $ s_axis_fifo_tvalid $end
$var reg 1 % s_axis_fifo_tlast $end
$var reg 1 & s_axis_fifo_tready $end
$var reg 16 ' m_axis_tdata[15:0] $end
$var reg 1 ( m_axis_tvalid $end
$var reg 1 ) m_axis_tready $end
$var reg 1 * sim_done $end
$scope module dut $end
$var reg 1 + clk $end
$var reg 1 , rst_n $end
$var reg 16 - s_axis_fifo_tdata[15:0] $end
$var reg 1 . s_axis_fifo_tvalid $end
$var reg 1 / s_axis_fifo_tlast $end
$var reg 1 0 s_axis_fifo_tready $end
$var reg 16 1 m_axis_tdata[15:0] $end
$var reg 1 2 m_axis_tvalid $end
$var reg 1 3 m_axis_tready $end
$var reg 1 4 s_axis_fifo_tready_r $end
$var reg 1 5 m_axis_tvalid_r $end
$var reg 16 6 m_axis_tdata_r[15:0] $end
$comment state is not handled $end
$var reg 16 7 received_word[15:0] $end
$var reg 1 8 received_word_tlast_reg $end
$var reg 16 9 chk_word[15:0] $end
$upscope $end
$upscope $end
$enddefinitions $end
#0
0!
0"
b0000000000000000 #
0$
0%
1&
b0000000000000000 '
0(
1)
0*
0+
0,
b0000000000000000 -
0.
0/
10
b0000000000000000 1
02
13
14
05
b0000000000000000 6
b0000000000000000 7
08
b0000000000000000 9
#5000000
1!
1+
#10000000
0!
0+
#15000000
1!
1+
#20000000
0!
0+
#25000000
1!
1+
#30000000
0!
0+
#35000000
1!
1+
#40000000
0!
0+
#45000000
1!
1+
#50000000
0!
0+
#55000000
1!
1"
1+
1,
#60000000
0!
0+
#65000000
1!
b0000000000000001 #
1$
1+
b0000000000000001 -
1.
#70000000
0!
0+
#75000000
1!
0$
0&
b1010101001010101 '
1(
1+
0.
00
b1010101001010101 1
12
04
15
b1010101001010101 6
b0000000000000001 7
b0000000000000001 9
#80000000
0!
0+
#85000000
1!
b0000000000011110 '
1+
b0000000000011110 1
b0000000000011110 6
#90000000
0!
0+
#95000000
1!
b0000000000000001 '
1+
b0000000000000001 1
b0000000000000001 6
#100000000
0!
0+
#105000000
1!
b0000000000000010 #
1$
1&
0(
1+
b0000000000000010 -
1.
10
02
14
05
#110000000
0!
0+
#115000000
1!
0$
0&
b0000000000000010 '
1(
1+
0.
00
b0000000000000010 1
12
04
15
b0000000000000010 6
b0000000000000011 9
#120000000
0!
0+
#125000000
1!
b0000000000000011 #
1$
1&
0(
1+
b0000000000000011 -
1.
10
02
14
05
#130000000
0!
0+
#135000000
1!
0$
0&
b0000000000000011 '
1(
1+
0.
00
b0000000000000011 1
12
04
15
b0000000000000011 6
b0000000000000000 9
#140000000
0!
0+
#145000000
1!
b0000000000000100 #
1$
1&
0(
1+
b0000000000000100 -
1.
10
02
14
05
#150000000
0!
0+
#155000000
1!
0$
0&
b0000000000000100 '
1(
1+
0.
00
b0000000000000100 1
12
04
15
b0000000000000100 6
b0000000000000100 9
#160000000
0!
0+
#165000000
1!
b0000101010100001 #
1$
1&
0(
1+
b0000101010100001 -
1.
10
02
14
05
#170000000
0!
0+
#175000000
1!
0$
0&
b0000101010100001 '
1(
1+
0.
00
b0000101010100001 1
12
04
15
b0000101010100001 6
b0000101010100101 9
#180000000
0!
0+
#185000000
1!
b0000101010100010 #
1$
1&
0(
1+
b0000101010100010 -
1.
10
02
14
05
#190000000
0!
0+
#195000000
1!
0$
0&
b0000101010100010 '
1(
1+
0.
00
b0000101010100010 1
12
04
15
b0000101010100010 6
b0000000000000111 9
#200000000
0!
0+
#205000000
1!
b0000101010100011 #
1$
1&
0(
1+
b0000101010100011 -
1.
10
02
14
05
#210000000
0!
0+
#215000000
1!
0$
0&
b0000101010100011 '
1(
1+
0.
00
b0000101010100011 1
12
04
15
b0000101010100011 6
b0000101010100100 9
#220000000
0!
0+
#225000000
1!
b0000101110110001 #
1$
1&
0(
1+
b0000101110110001 -
1.
10
02
14
05
#230000000
0!
0+
#235000000
1!
0$
0&
b0000101110110001 '
1(
1+
0.
00
b0000101110110001 1
12
04
15
b0000101110110001 6
b0000000100010101 9
#240000000
0!
0+
#245000000
1!
b0000101110110010 #
1$
1&
0(
1+
b0000101110110010 -
1.
10
02
14
05
#250000000
0!
0+
#255000000
1!
0$
0&
b0000101110110010 '
1(
1+
0.
00
b0000101110110010 1
12
04
15
b0000101110110010 6
b0000101010100111 9
#260000000
0!
0+
#265000000
1!
b0000101110110011 #
1$
1&
0(
1+
b0000101110110011 -
1.
10
02
14
05
#270000000
0!
0+
#275000000
1!
0$
0&
b0000101110110011 '
1(
1+
0.
00
b0000101110110011 1
12
04
15
b0000101110110011 6
b0000000100010100 9
#280000000
0!
0+
#285000000
1!
b0000000011000001 #
1$
1&
0(
1+
b0000000011000001 -
1.
10
02
14
05
#290000000
0!
0+
#295000000
1!
0$
0&
b0000000011000001 '
1(
1+
0.
00
b0000000011000001 1
12
04
15
b0000000011000001 6
b0000000111010101 9
#300000000
0!
0+
#305000000
1!
b0000110111010001 #
1$
1&
0(
1+
b0000110111010001 -
1.
10
02
14
05
#310000000
0!
0+
#315000000
1!
0$
0&
b0000110111010001 '
1(
1+
0.
00
b0000110111010001 1
12
04
15
b0000110111010001 6
b0000110000000100 9
#320000000
0!
0+
#325000000
1!
b0000110111010010 #
1$
1&
0(
1+
b0000110111010010 -
1.
10
02
14
05
#330000000
0!
0+
#335000000
1!
0$
0&
b0000110111010010 '
1(
1+
0.
00
b0000110111010010 1
12
04
15
b0000110111010010 6
b0000000111010110 9
#340000000
0!
0+
#345000000
1!
b0000110111010011 #
1$
1&
0(
1+
b0000110111010011 -
1.
10
02
14
05
#350000000
0!
0+
#355000000
1!
0$
0&
b0000110111010011 '
1(
1+
0.
00
b0000110111010011 1
12
04
15
b0000110111010011 6
b0000110000000101 9
#360000000
0!
0+
#365000000
1!
b0000000011100001 #
1$
1%
1&
0(
1+
b0000000011100001 -
1.
1/
10
02
14
05
#370000000
0!
0+
#375000000
1!
0$
0%
0&
b0000000011100001 '
1(
1+
0.
0/
00
b0000000011100001 1
12
04
15
b0000000011100001 6
18
b0000110011100100 9
#380000000
0!
0+
#385000000
1!
b0000110011100100 '
1+
b0000110011100100 1
b0000110011100100 6
#390000000
0!
0+
#395000000
1!
b0001000000000001 #
1$
1&
0(
1+
b0001000000000001 -
1.
10
02
14
05
b0000000000000000 9
#400000000
0!
0+
#405000000
1!
0$
0&
b1010101001010101 '
1(
1+
0.
00
b1010101001010101 1
12
04
15
b1010101001010101 6
b0001000000000001 7
b0001000000000001 9
#410000000
0!
0+
#415000000
1!
b0000000000011110 '
1+
b0000000000011110 1
b0000000000011110 6
#420000000
0!
0+
#425000000
1!
b0001000000000001 '
1+
b0001000000000001 1
b0001000000000001 6
#430000000
0!
0+
#435000000
1!
b0001000000000010 #
1$
1&
0(
1+
b0001000000000010 -
1.
10
02
14
05
#440000000
0!
0+
#445000000
1!
0$
0&
b0001000000000010 '
1(
1+
0.
00
b0001000000000010 1
12
04
15
b0001000000000010 6
08
b0000000000000011 9
#450000000
0!
0+
#455000000
1!
b0001000000000011 #
1$
1&
0(
1+
b0001000000000011 -
1.
10
02
14
05
#460000000
0!
0+
#465000000
1!
0$
0&
b0001000000000011 '
1(
1+
0.
00
b0001000000000011 1
12
04
15
b0001000000000011 6
b0001000000000000 9
#470000000
0!
0+
#475000000
1!
b0001000000000100 #
1$
1&
0(
1+
b0001000000000100 -
1.
10
02
14
05
#480000000
0!
0+
#485000000
1!
0$
0&
b0001000000000100 '
1(
1+
0.
00
b0001000000000100 1
12
04
15
b0001000000000100 6
b0000000000000100 9
#490000000
0!
0+
#495000000
1!
b0001101010100001 #
1$
1&
0(
1+
b0001101010100001 -
1.
10
02
14
05
#500000000
0!
0+
#505000000
1!
0$
0&
b0001101010100001 '
1(
1+
0.
00
b0001101010100001 1
12
04
15
b0001101010100001 6
b0001101010100101 9
#510000000
0!
0+
#515000000
1!
b0001101010100010 #
1$
1&
0(
1+
b0001101010100010 -
1.
10
02
14
05
#520000000
0!
0+
#525000000
1!
0$
0&
b0001101010100010 '
1(
1+
0.
00
b0001101010100010 1
12
04
15
b0001101010100010 6
b0000000000000111 9
#530000000
0!
0+
#535000000
1!
b0001101010100011 #
1$
1&
0(
1+
b0001101010100011 -
1.
10
02
14
05
#540000000
0!
0+
#545000000
1!
0$
0&
b0001101010100011 '
1(
1+
0.
00
b0001101010100011 1
12
04
15
b0001101010100011 6
b0001101010100100 9
#550000000
0!
0+
#555000000
1!
b0001101110110001 #
1$
1&
0(
1+
b0001101110110001 -
1.
10
02
14
05
#560000000
0!
0+
#565000000
1!
0$
0&
b0001101110110001 '
1(
1+
0.
00
b0001101110110001 1
12
04
15
b0001101110110001 6
b0000000100010101 9
#570000000
0!
0+
#575000000
1!
b0001101110110010 #
1$
1&
0(
1+
b0001101110110010 -
1.
10
02
14
05
#580000000
0!
0+
#585000000
1!
0$
0&
b0001101110110010 '
1(
1+
0.
00
b0001101110110010 1
12
04
15
b0001101110110010 6
b0001101010100111 9
#590000000
0!
0+
#595000000
1!
b0001101110110011 #
1$
1&
0(
1+
b0001101110110011 -
1.
10
02
14
05
#600000000
0!
0+
#605000000
1!
0$
0&
b0001101110110011 '
1(
1+
0.
00
b0001101110110011 1
12
04
15
b0001101110110011 6
b0000000100010100 9
#610000000
0!
0+
#615000000
1!
b0001000011000001 #
1$
1&
0(
1+
b0001000011000001 -
1.
10
02
14
05
#620000000
0!
0+
#625000000
1!
0$
0&
b0001000011000001 '
1(
1+
0.
00
b0001000011000001 1
12
04
15
b0001000011000001 6
b0001000111010101 9
#630000000
0!
0+
#635000000
1!
b0001110111010001 #
1$
1&
0(
1+
b0001110111010001 -
1.
10
02
14
05
#640000000
0!
0+
#645000000
1!
0$
0&
b0001110111010001 '
1(
1+
0.
00
b0001110111010001 1
12
04
15
b0001110111010001 6
b0000110000000100 9
#650000000
0!
0+
#655000000
1!
b0001110111010010 #
1$
1&
0(
1+
b0001110111010010 -
1.
10
02
14
05
#660000000
0!
0+
#665000000
1!
0$
0&
b0001110111010010 '
1(
1+
0.
00
b0001110111010010 1
12
04
15
b0001110111010010 6
b0001000111010110 9
#670000000
0!
0+
#675000000
1!
b0001110111010011 #
1$
1&
0(
1+
b0001110111010011 -
1.
10
02
14
05
#680000000
0!
0+
#685000000
1!
0$
0&
b0001110111010011 '
1(
1+
0.
00
b0001110111010011 1
12
04
15
b0001110111010011 6
b0000110000000101 9
#690000000
0!
0+
#695000000
1!
b0001000011100001 #
1$
1%
1&
0(
1+
b0001000011100001 -
1.
1/
10
02
14
05
#700000000
0!
0+
#705000000
1!
0$
0%
0&
b0001000011100001 '
1(
1+
0.
0/
00
b0001000011100001 1
12
04
15
b0001000011100001 6
18
b0001110011100100 9
#710000000
0!
0+
#715000000
1!
b0001110011100100 '
1+
b0001110011100100 1
b0001110011100100 6
#720000000
0!
0+
#725000000
1!
1&
0(
1*
1+
10
02
14
05
b0000000000000000 9
